kickpython/__init__.py
kickpython/api.py
kickpython/py.typed
kickpython/examples/listen_all_channels.py
kickpython/examples/oauth.py
kickpython-0.1.5.dist-info/LICENSE
kickpython-0.1.5.dist-info/METADATA
kickpython-0.1.5.dist-info/WHEEL
kickpython-0.1.5.dist-info/top_level.txt
kickpython-0.1.5.dist-info/RECORD
