Metadata-Version: 2.2
Name: kickpython
Version: 0.1.5
Summary: Python wrapper for Kick.com API
Home-page: https://github.com/berkay-digital/kickpython
Author: berkay.digital
Author-email: "berkay.digital" <contact@berkay.digital>
License: MIT
Project-URL: Homepage, https://github.com/berkay-digital/kickpython
Project-URL: Documentation, https://github.com/berkay-digital/kickpython/tree/main/docs
Project-URL: Repository, https://github.com/berkay-digital/kickpython.git
Project-URL: Issues, https://github.com/berkay-digital/kickpython/issues
Requires-Python: >=3.6
License-File: LICENSE
Dynamic: author
Dynamic: home-page
Dynamic: requires-python
